keyv.py
keyv-0.4.0.dist-info/LICENSE
keyv-0.4.0.dist-info/METADATA
keyv-0.4.0.dist-info/WHEEL
keyv-0.4.0.dist-info/RECORD
