Metadata-Version: 2.3
Name: keyv
Version: 0.4.0
Summary: A lightweight, file-based NoSQL key-value database using sqlite3, designed for simple and practical uses without external dependencies.
Author: renanmoretto
Author-email: renan_moretto@outlook.com
Requires-Python: >=3.8
Classifier: Programming Language :: Python :: 3
Classifier: Programming Language :: Python :: 3.8
Classifier: Programming Language :: Python :: 3.9
Classifier: Programming Language :: Python :: 3.10
Classifier: Programming Language :: Python :: 3.11
Classifier: Programming Language :: Python :: 3.12
Classifier: Programming Language :: Python :: 3.13
Project-URL: Repository, https://github.com/renanmoretto/keyv
